logs/annotated/mono_out.v
//      // verilator_coverage annotation
        module mono_out(
%000001 	input [7:0] keycode,
%000000 	output [2:0] note
        );
        
%000001 reg [2:0] note_r = 3'd0;
%000000 reg br = 1'b0;
        
        assign note = note_r;
        
%000003 always @ (keycode) begin
%000000 	if (br == 1'b0) begin
%000003 		case(keycode)
%000000 			8'h16:note_r <= 3'd1; // Keycode for 1
%000000 			8'h1E:note_r <= 3'd2; // 2
%000000 			8'h26:note_r <= 3'd3; // 3
%000000 			8'hF0:br  <= 1'd1;
%000003 			default:;
        		endcase
%000000 	end else begin
%000000 		br <= 1'b0;
%000000 		case(keycode)
%000000 			8'h16:begin
%000000 				if (note_r == 3'd1) begin
%000000 					note_r <= 3'd0;
        				end
        			end
%000000 			8'h1E:begin
%000000 				if (note_r == 3'd2) begin
%000000 					note_r <= 3'd0;
        				end
        			end
%000000 			8'h26:begin
%000000 				if (note_r == 3'd3) begin
%000000 					note_r <= 3'd0;
        				end
        			end
%000000 			8'hF0:br <= 1'b1;
%000000 			default:;
        		endcase
        	end
        end
        endmodule

kbd_infc.v
module kbd_infc(
	input kbdclk,
	input kbddata,
	output reg [3:0] s,
	output reg [7:0] word
);




reg [7:0] word_r;
wire [3:0] ns;

initial begin
	word = 8'h0;
	word_r = 8'h0;
	s = 4'd0;
end

assign ns = (s == 4'hB) ? 4'b0001 : s + 4'b0001;

always@(negedge kbdclk) begin
	s <= ns;
	case (s) 
		4'h1:word_r[0] <= kbddata;	

		4'h2:word_r[1] <= kbddata;

		4'h3:word_r[2] <= kbddata;

		4'h4:word_r[3] <= kbddata;
		
		4'h5:word_r[4] <= kbddata;
		
		4'h6:word_r[5] <= kbddata;
		4'h7:word_r[6] <= kbddata;
		4'h8:word_r[7] <= kbddata;
		4'h9:word  <= word_r;
		default:;
	endcase
end


   initial begin
      if ($test$plusargs("trace") != 0) begin
         $display("[%0t] Tracing to logs/vlt_dump.vcd...\n", $time);
         $dumpfile("logs/vlt_dump.vcd");
         $dumpvars();
      end
      $display("[%0t] Model running...\n", $time);
   end



endmodule

logs/annotated/top.v
//      // verilator_coverage annotation
 000045 module top (input clk,
 000011 	input data,
%000003 	output reg [3:0] s,
%000001 	output reg [7:0] word,
%000000 	output reg [2:0] note
        );	
        
        
        	kbd_infc kbd_infc (
        		.kbdclk(clk),
        		.kbddata(data),
        		.s(s),
        		.word(word)
        	);
        
        	mono_out mono_out (
        		.keycode(word),
        		.note(note)
        	);
        
        
        endmodule

logs/vlt_dump.vcd
$version Generated by VerilatedVcd $end
$timescale 1ps $end

 $scope module TOP $end
  $var wire  1 # clk $end
  $var wire  1 $ data $end
  $var wire  3 ' note [2:0] $end
  $var wire  4 % s [3:0] $end
  $var wire  8 & word [7:0] $end
  $scope module top $end
   $var wire  1 # clk $end
   $var wire  1 $ data $end
   $var wire  3 ' note [2:0] $end
   $var wire  4 % s [3:0] $end
   $var wire  8 & word [7:0] $end
   $scope module kbd_infc $end
    $var wire  1 # kbdclk $end
    $var wire  1 $ kbddata $end
    $var wire  4 ) ns [3:0] $end
    $var wire  4 % s [3:0] $end
    $var wire  8 & word [7:0] $end
    $var wire  8 ( word_r [7:0] $end
   $upscope $end
   $scope module mono_out $end
    $var wire  1 + br $end
    $var wire  8 & keycode [7:0] $end
    $var wire  3 ' note [2:0] $end
    $var wire  3 * note_r [2:0] $end
   $upscope $end
  $upscope $end
 $upscope $end
$enddefinitions $end


#2
1#
1$
b0000 %
b00000000 &
b000 '
b00000000 (
b0001 )
b000 *
0+
#3
#4
#5
#6
#7
#8
#9
#10
#11
#12
#13
#14
#15
#16
#17
#18
0$
#19
0#
b0001 %
b0010 )
#20
1#
1$
#21
0#
b0010 %
b00000001 (
b0011 )
#22
1#
0$
#23
0#
b0011 %
b0100 )
#24
1#
#25
0#
b0100 %
b0101 )
#26
1#
1$
#27
0#
b0101 %
b00001001 (
b0110 )
#28
1#
0$
#29
0#
b0110 %
b0111 )
#30
1#
#31
0#
b0111 %
b1000 )
#32
1#
1$
#33
0#
b1000 %
b01001001 (
b1001 )
#34
1#
#35
0#
b1001 %
b11001001 (
b1010 )
#36
1#
#37
0#
b1010 %
b11001001 &
b1011 )
#38
1#
#39
0#
b1011 %
b0001 )
#40
1#
#41
#42
#43
#44
0$
#45
0#
b0001 %
b0010 )
#46
1#
#47
0#
b0010 %
b11001000 (
b0011 )
#48
1#
#49
0#
b0011 %
b0100 )
#50
1#
#51
0#
b0100 %
b0101 )
#52
1#
1$
#53
0#
b0101 %
b0110 )
#54
1#
#55
0#
b0110 %
b11011000 (
b0111 )
#56
1#
#57
0#
b0111 %
b11111000 (
b1000 )
#58
1#
#59
0#
b1000 %
b1001 )
#60
1#
0$
#61
0#
b1001 %
b01111000 (
b1010 )
#62
1#
1$
#63
0#
b1010 %
b01111000 &
b1011 )
#64
1#
#65
0#
b1011 %
b0001 )
